{
  "id": "3826077814",
  "pages": 248,
  "title": "Hermeneutische Phänomenologie der Zeitlichkeit des Daseins: Zwei Freiburger Seminare zu Martin Heideggers ,Sein und Zeit'",
  "cover": "https://m.media-amazon.com/images/I/417s55PtxpL._SL1500_.jpg",
  "publication_date": "2023-01-23T00:00:00+01:00",
  "language": "Allemand",
  "publisher": "Königshausen \u0026 Neumann",
  "description": "",
  "price": 37.46,
  "rating": -1,
  "authors": [
    {
      "id": "",
      "name": "Friedrich-Wilhelm Von Herrmann",
      "link": "/s/ref=dp_byline_sr_book_1?ie=UTF8\u0026field-author=Friedrich-Wilhelm+Von+Herrmann\u0026text=Friedrich-Wilhelm+Von+Herrmann\u0026sort=relevancerank\u0026search-alias=books-fr-intl-us"
    },
    {
      "id": "",
      "name": "Mark Michalski",
      "link": "/s/ref=dp_byline_sr_book_2?ie=UTF8\u0026field-author=Mark+Michalski\u0026text=Mark+Michalski\u0026sort=relevancerank\u0026search-alias=books-fr-intl-us"
    }
  ],
  "dimensions": {
    "height": 24,
    "depth": 2.3,
    "width": 16
  },
  "is_gbook": false
}